wavebin/__main__.py
wavebin/export.py
wavebin/interface.py
wavebin/plot.py
wavebin/wave.py
wavebin-2.3.1.dist-info/LICENSE
wavebin-2.3.1.dist-info/METADATA
wavebin-2.3.1.dist-info/WHEEL
wavebin-2.3.1.dist-info/top_level.txt
wavebin-2.3.1.dist-info/RECORD
