Metadata-Version: 2.1
Name: wavebin
Version: 2.3.1
Summary: Waveform capture viewer for Agilent, Keysight and Rigol oscilloscopes
Home-page: https://github.com/sam210723/wavebin
Author: sam210723
Author-email: pypi@vksdr.com
Classifier: Topic :: Scientific/Engineering :: Visualization
Classifier: Environment :: Console
Classifier: Environment :: X11 Applications :: Qt
Classifier: Intended Audience :: Developers
Classifier: Intended Audience :: Science/Research
Classifier: License :: OSI Approved :: MIT License
Classifier: Development Status :: 5 - Production/Stable
Classifier: Natural Language :: English
Classifier: Programming Language :: Python
Classifier: Programming Language :: Python :: 3
Classifier: Programming Language :: Python :: 3.6
Classifier: Programming Language :: Python :: 3.7
Classifier: Programming Language :: Python :: 3.8
Classifier: Programming Language :: Python :: 3.9
Requires-Python: >3.6
License-File: LICENSE
Requires-Dist: numpy
Requires-Dist: pyqt5
Requires-Dist: pyqtgraph
